upath.cpython-37m-darwin.so
upath-1.0.1.dist-info/LICENSE
upath-1.0.1.dist-info/METADATA
upath-1.0.1.dist-info/WHEEL
upath-1.0.1.dist-info/top_level.txt
upath-1.0.1.dist-info/RECORD
