Metadata-Version: 2.1
Name: upath
Version: 1.0.1
Summary: 
Home-page: https://github.com/aoprisor/upath
Author: Georgian-Andrei Oprișor
Author-email: gaoprisor@gmail.com
License: MIT
Platform: UNKNOWN
Classifier: Programming Language :: Python :: 3
